svo_client/__init__.py
svo_client/chunker_client.py
svo_client/cli.py
svo_client/client_config_generator.py
svo_client/config_loader.py
svo_client/config_tools.py
svo_client/config_utils.py
svo_client/error_mapper.py
svo_client/errors.py
svo_client/result_parser.py
svo_client/server_config_generator.py
svo_client/text_utils.py
svo_client/examples/__init__.py
svo_client/examples/example_usage.py
svo_client-2.2.8.data/scripts/generate_client_config.py
svo_client-2.2.8.data/scripts/validate_client_config.py
svo_client-2.2.8.dist-info/METADATA
svo_client-2.2.8.dist-info/WHEEL
svo_client-2.2.8.dist-info/entry_points.txt
svo_client-2.2.8.dist-info/top_level.txt
svo_client-2.2.8.dist-info/RECORD
