Metadata-Version: 2.4
Name: svo-client
Version: 2.2.8
Summary: Async client for SVO semantic chunker microservice.
Home-page: https://github.com/your_org/svo_client
Author: Vasiliy Zdanovskiy
Author-email: vasilyvz@gmail.com
Classifier: Programming Language :: Python :: 3
Classifier: Programming Language :: Python :: 3.8
Classifier: Programming Language :: Python :: 3.9
Classifier: Programming Language :: Python :: 3.10
Classifier: Programming Language :: Python :: 3.11
Classifier: Programming Language :: Python :: 3.12
Classifier: License :: OSI Approved :: MIT License
Classifier: Operating System :: OS Independent
Classifier: Development Status :: 4 - Beta
Classifier: Intended Audience :: Developers
Classifier: Topic :: Software Development :: Libraries :: Python Modules
Requires-Python: >=3.8
Requires-Dist: pydantic>=2.0.0
Requires-Dist: chunk_metadata_adapter>=3.3.3
Requires-Dist: mcp-proxy-adapter>=6.9.103
Requires-Dist: aiohttp>=3.8.0
Requires-Dist: httpx>=0.24.0
Dynamic: author
Dynamic: author-email
Dynamic: classifier
Dynamic: description
Dynamic: description-content-type
Dynamic: home-page
Dynamic: requires-dist
Dynamic: requires-python
Dynamic: summary
